[
    {
        "content": "<p>Jā, diezgan droši, ka tuvums Rīgai.</p>",
        "id": 390501383,
        "sender_full_name": "Rihards Olups",
        "timestamp": 1694519099
    },
    {
        "content": "<p>Varbūt jāpamēģina pielikt RIX'am <a href=\"https://wiki.openstreetmap.org/wiki/Tag%3Ashort_name%3DRiga\">short_name=Riga</a>?</p>",
        "id": 390501599,
        "sender_full_name": "i-ky",
        "timestamp": 1694519190
    },
    {
        "content": "<p>Šķiet OK, nevaru iedomāties, kādēļ ne.</p>",
        "id": 390503600,
        "sender_full_name": "Rihards Olups",
        "timestamp": 1694519939
    }
]